snsary/__init__.py
snsary/contrib/__init__.py
snsary/contrib/awair.py
snsary/contrib/datastax.py
snsary/contrib/grafana.py
snsary/contrib/influxdb.py
snsary/contrib/octopus.py
snsary/contrib/pimoroni.py
snsary/contrib/psutil.py
snsary/contrib/pypms.py
snsary/contrib/adafruit/__init__.py
snsary/contrib/adafruit/generic.py
snsary/contrib/adafruit/sgp30.py
snsary/contrib/google/__init__.py
snsary/contrib/google/bigquery.py
snsary/contrib/google/reading_pb2.py
snsary/functions/__init__.py
snsary/functions/filter.py
snsary/functions/function.py
snsary/functions/rename.py
snsary/functions/window.py
snsary/functions/window_average.py
snsary/functions/window_summary.py
snsary/models/__init__.py
snsary/models/reading.py
snsary/outputs/__init__.py
snsary/outputs/batch_output.py
snsary/outputs/mock_output.py
snsary/outputs/output.py
snsary/sources/__init__.py
snsary/sources/mock_sensor.py
snsary/sources/multi_source.py
snsary/sources/poller.py
snsary/sources/polling_sensor.py
snsary/sources/sensor.py
snsary/sources/source.py
snsary/streams/__init__.py
snsary/streams/async_stream.py
snsary/streams/func_stream.py
snsary/streams/simple_stream.py
snsary/streams/stream.py
snsary/system/__init__.py
snsary/system/backend.py
snsary/system/service.py
snsary/utils/__init__.py
snsary/utils/logging.py
snsary/utils/request.py
snsary/utils/scraper.py
snsary/utils/storage/__init__.py
snsary/utils/storage/backend.py
snsary/utils/storage/max_tracker.py
snsary/utils/storage/null_tracker.py
snsary/utils/storage/tracker.py
snsary/utils/tracing/__init__.py
snsary/utils/tracing/config.py
snsary/utils/tracing/core.py
snsary/utils/tracing/history.py
snsary/utils/tracing/monitors.py
snsary/utils/tracing/registry.py
snsary/utils/tracing/sample.py
snsary-0.1.1.dist-info/LICENCE
snsary-0.1.1.dist-info/METADATA
snsary-0.1.1.dist-info/WHEEL
snsary-0.1.1.dist-info/top_level.txt
snsary-0.1.1.dist-info/RECORD
