Metadata-Version: 2.1
Name: snsary
Version: 0.1.1
Summary: A framework for sensor metrics
Home-page: https://github.com/benthorner/snsary
Author: Ben Thorner
Author-email: benthorner@users.noreply.github.com
Project-URL: Bug Tracker, https://github.com/benthorner/snsary/issues
Classifier: Programming Language :: Python :: 3
Classifier: License :: OSI Approved :: MIT License
Classifier: Operating System :: Unix
Requires-Python: >=3.9
License-File: LICENCE
Requires-Dist: cachetools >=5.3.0
Requires-Dist: wrapt >=1.14.1
Provides-Extra: adafruit
Provides-Extra: all
Requires-Dist: requests >=2.28.2 ; extra == 'all'
Requires-Dist: pyrfc3339 >=1.1 ; extra == 'all'
Requires-Dist: gql[requests] >=3.4.0 ; extra == 'all'
Requires-Dist: google-cloud-bigquery-storage >=2.18.1 ; extra == 'all'
Requires-Dist: influxdb-client >=1.36.0 ; extra == 'all'
Requires-Dist: psutil >=5.9.4 ; extra == 'all'
Requires-Dist: pypms >=0.7.1 ; extra == 'all'
Provides-Extra: awair
Requires-Dist: requests >=2.28.2 ; extra == 'awair'
Requires-Dist: pyrfc3339 >=1.1 ; extra == 'awair'
Provides-Extra: datastax
Requires-Dist: gql[requests] >=3.4.0 ; extra == 'datastax'
Provides-Extra: google
Requires-Dist: google-cloud-bigquery-storage >=2.18.1 ; extra == 'google'
Provides-Extra: grafana
Requires-Dist: requests >=2.28.2 ; extra == 'grafana'
Provides-Extra: influxdb
Requires-Dist: influxdb-client >=1.36.0 ; extra == 'influxdb'
Provides-Extra: octopus
Requires-Dist: requests >=2.28.2 ; extra == 'octopus'
Requires-Dist: pyrfc3339 >=1.1 ; extra == 'octopus'
Provides-Extra: pimoroni
Provides-Extra: psutil
Requires-Dist: psutil >=5.9.4 ; extra == 'psutil'
Provides-Extra: pypms
Requires-Dist: pypms >=0.7.1 ; extra == 'pypms'
